pyarn/__init__.py
pyarn/lexer.py
pyarn/lexer_wrapper.py
pyarn/lockfile.py
pyarn/parser.py
pyarn/parsetab.py
pyarn-0.3.0.dist-info/LICENSE
pyarn-0.3.0.dist-info/METADATA
pyarn-0.3.0.dist-info/WHEEL
pyarn-0.3.0.dist-info/top_level.txt
pyarn-0.3.0.dist-info/RECORD
