Metadata-Version: 2.1
Name: pyarn
Version: 0.3.0
Summary: Yarn JS package manager lockfile parser
Home-page: https://github.com/containerbuildsystem/pyarn
Author: Red Hat, Inc.
Author-email: athos@redhat.com
License: GPLv3+
Keywords: Yarn,JavaScript,lockfile
Platform: any
Classifier: Development Status :: 1 - Planning
Classifier: Intended Audience :: Developers
Classifier: License :: OSI Approved :: GNU General Public License v3 or later (GPLv3+)
Classifier: Programming Language :: Python :: 3
Classifier: Programming Language :: Python :: 3.7
Classifier: Programming Language :: Python :: 3.8
Classifier: Programming Language :: Python :: 3 :: Only
Requires-Python: >=3.7
License-File: LICENSE
Requires-Dist: ply
